{
    "id": 10254,
    "level": "N3",
    "title": "させてください",
    "means": [
        {
            "id": 10254100,
            "format": "V（使役形）＋てください",
            "mean": "  请允许我～ ",
            "type": [
                "依頼"
            ],
            "examples": [
                {
                    "id": 19779,
                    "ruby": "<ruby>市役所<rt>しやくしょ</rt></ruby>へ<ruby>行<rt>い</rt></ruby>かなければならないので、<ruby>今日<rt>きょう</rt></ruby>は<ruby>早<rt>はや</rt></ruby>く<ruby>帰<rt>かえ</rt></ruby>らせてください。",
                    "explain": "我今天必须去市政府，请允许我早点下班吧。",
                    "other": ""
                },
                {
                    "id": 19780,
                    "ruby": "<ruby>後<rt>ご</rt></ruby>で<ruby>取<rt>と</rt></ruby>りに<ruby>来<rt>き</rt></ruby>ますから、ここにちょっとかばんを<ruby>置<rt>お</rt></ruby>かせてください。",
                    "explain": "请允许我把包放这一下，一会儿就过来取。",
                    "other": ""
                },
                {
                    "id": 19781,
                    "ruby": "９<ruby>時<rt>じ</rt></ruby>ごろこちらの<ruby>方<rt>ほう</rt></ruby>から<ruby>電話<rt>でんわ</rt></ruby>をかけさせてください。",
                    "explain": "9点钟左右，请允许我给你们打电话。",
                    "other": ""
                },
                {
                    "id": 19782,
                    "ruby": "その<ruby>仕事<rt>しごと</rt></ruby>はぜひわたしにさせてくださいませんか。",
                    "explain": "那个工作，请一定让我来做。",
                    "other": ""
                }
            ]
        }
    ]
}