{
    "id": "articles20200811kei00s00s008000c",
    "title": "社会　７５回目　長崎原爆の日　平和へ連帯訴える",
    "ruby": "",
    "time": "2020年8月11日",
    "imgurl": "https://cdn.mainichi.jp/vol1/2020/08/11/20200811kei00s00s020000p/0c6.jpg?1",
    "fromUrl": "https://mainichi.jp/articles/20200811/kei/00s/00s/008000c",
    "body": [
        {
            "type": "ruby",
            "ruby": "<ruby>長崎<rt>ながさき</rt></ruby>は９<ruby>日<rt>ここのか</rt></ruby>、アメリカ<ruby>軍<rt>ぐん</rt></ruby>による<ruby>原子爆弾<rt>げんしばくだん</rt></ruby>の<ruby>投下<rt>とうか</rt></ruby>で<ruby>約<rt>やく</rt></ruby>７<ruby>万<rt>まん</rt></ruby>４０００<ruby>人<rt>にん</rt></ruby>が<ruby>犠牲<rt>ぎせい</rt></ruby>になった<ruby>日<rt>ひ</rt></ruby>から７５<ruby>年<rt>ねん</rt></ruby>を<ruby>迎<rt>むか</rt></ruby>えました。<ruby>長崎市<rt>ながさきし</rt></ruby>の<ruby>平和公園<rt>へいわこうえん</rt></ruby>であった<ruby>平和<rt>へいわ</rt></ruby><ruby>祈念<rt>きねん</rt></ruby><ruby>式典<rt>しきてん</rt></ruby>で、<ruby>田上富久<rt>たうえとみひさ</rt></ruby><ruby>市長<rt>しちょう</rt></ruby>は「<ruby>新型<rt>しんがた</rt></ruby>コロナウイルスも<ruby>核問題<rt>かくもんだい</rt></ruby>も<ruby>地球<rt>ちきゅう</rt></ruby>にすむみんなが<ruby>当事者<rt>とうじしゃ</rt></ruby>だ」とし、<ruby>各国<rt>かっこく</rt></ruby>の<ruby>連帯<rt>れんたい</rt></ruby>を<ruby>訴<rt>うった</rt></ruby>えました。",
            "origin": "長崎は９日、アメリカ軍による原子爆弾の投下で約７万４０００人が犠牲になった日から７５年を迎えました。長崎市の平和公園であった平和祈念式典で、田上富久市長は「新型コロナウイルスも核問題も地球にすむみんなが当事者だ」とし、各国の連帯を訴えました。"
        },
        {
            "type": "ruby",
            "ruby": "<ruby>田上<rt>たうえ</rt></ruby><ruby>市長<rt>しちょう</rt></ruby>は、<ruby>平和宣言<rt>へいわせんげん</rt></ruby>で、２０１７<ruby>年<rt>ねん</rt></ruby>に<ruby>国連<rt>こくれん</rt></ruby>で<ruby>作<rt>つく</rt></ruby>られた<ruby>核兵器禁止条約<rt>かくへいききんしじょうやく</rt></ruby>に<ruby>日本<rt>にっぽん</rt></ruby>が<ruby>参加<rt>さんか</rt></ruby>していないことを<ruby>批判<rt>ひはん</rt></ruby>しました。<ruby>早<rt>はや</rt></ruby>く<ruby>参加<rt>さんか</rt></ruby>するよう<ruby>政府<rt>せいふ</rt></ruby>に<ruby>迫<rt>せま</rt></ruby>りましたが、<ruby>安倍晋三<rt>あべしんぞう</rt></ruby><ruby>総理大臣<rt>そうりだいじん</rt></ruby>は<ruby>今年<rt>ことし</rt></ruby>も<ruby>式典<rt>しきてん</rt></ruby>あいさつで<ruby>条約<rt>じょうやく</rt></ruby>に<ruby>触<rt>ふ</rt></ruby>れず、その<ruby>後<rt>ご</rt></ruby>の<ruby>会見<rt>かいけん</rt></ruby>で、<ruby>条約<rt>じょうやく</rt></ruby>に<ruby>参加<rt>さんか</rt></ruby>しない<ruby>考<rt>かんが</rt></ruby>えを<ruby>改<rt>あらた</rt></ruby>めて<ruby>示<rt>しめ</rt></ruby>しました。",
            "origin": "田上市長は、平和宣言で、２０１７年に国連で作られた核兵器禁止条約に日本が参加していないことを批判しました。早く参加するよう政府に迫りましたが、安倍晋三総理大臣は今年も式典あいさつで条約に触れず、その後の会見で、条約に参加しない考えを改めて示しました。"
        },
        {
            "type": "ruby",
            "ruby": "<ruby>長崎市松山町<rt>ながさきしまつやままち</rt></ruby>の<ruby>爆心地<rt>ばくしんち</rt></ruby><ruby>公園<rt>こうえん</rt></ruby>にはこの<ruby>日朝<rt>ひあさ</rt></ruby>から、<ruby>高校生<rt>こうこうせい</rt></ruby>たちが<ruby>集<rt>あつ</rt></ruby>まりました。<ruby>原爆<rt>げんばく</rt></ruby><ruby>落下<rt>らっか</rt></ruby><ruby>中心地<rt>ちゅうしんち</rt></ruby><ruby>碑<rt>ひ</rt></ruby>を<ruby>囲<rt>かこ</rt></ruby>む「<ruby>人間<rt>にんげん</rt></ruby>の<ruby>鎖<rt>くさり</rt></ruby>」で<ruby>核兵器<rt>かくへいき</rt></ruby><ruby>廃絶<rt>はいぜつ</rt></ruby>への<ruby>思<rt>おも</rt></ruby>いを<ruby>表現<rt>ひょうげん</rt></ruby>しました。",
            "origin": "長崎市松山町の爆心地公園にはこの日朝から、高校生たちが集まりました。原爆落下中心地碑を囲む「人間の鎖」で核兵器廃絶への思いを表現しました。"
        }
    ],
    "voiceurl": "",
    "movieurl": "",
    "newimage": "https://cdn.mainichi.jp/vol1/2020/08/11/20200811kei00s00s020000p/0c6.jpg?1",
    "newsmovie": "",
    "path": "appdata/daynews/articles20200811kei00s00s008000c.json"
}