{
    "id": "articles20200910kei00s00s002000c",
    "title": "ケロ平　岩手県",
    "ruby": "",
    "time": "2020年9月10日",
    "imgurl": "https://cdn.mainichi.jp/vol1/2020/09/10/20200910kei00s00s026000p/0c6.jpg?1",
    "fromUrl": "https://mainichi.jp/articles/20200910/kei/00s/00s/002000c",
    "body": [
        {
            "type": "h2",
            "ruby": "ぴょんぴょん<ruby>岩手<rt>いわて</rt></ruby>の<ruby>魅力<rt>みりょく</rt></ruby>を<ruby>伝<rt>つた</rt></ruby>えます",
            "origin": "ぴょんぴょん岩手の魅力を伝えます"
        },
        {
            "type": "ruby",
            "ruby": "つい「けろへい」と<ruby>読<rt>よ</rt></ruby>んでしまいそうになりますが、<ruby>実<rt>じつ</rt></ruby>は<ruby>読<rt>よ</rt></ruby>み<ruby>方<rt>かた</rt></ruby>は「けろひら」なところがミソ。<ruby>岩手県<rt>いわてけん</rt></ruby>の<ruby>世界遺産<rt>せかいいさん</rt></ruby>・<ruby>平泉<rt>ひらいずみ</rt></ruby>のＰＲキャラクターで２０１４<ruby>年<rt>ねん</rt></ruby>から<ruby>活動<rt>かつどう</rt></ruby>しています。<ruby>名前<rt>なまえ</rt></ruby>は<ruby>平泉<rt>ひらいずみ</rt></ruby>の「<ruby>平<rt>ひら</rt></ruby>」を<ruby>表<rt>あらわ</rt></ruby>していたんですね。<ruby>奥州藤原氏<rt>おうしゅうふじわらし</rt></ruby>が<ruby>政治<rt>せいじ</rt></ruby>の<ruby>拠点<rt>きょてん</rt></ruby>にしていた<ruby>平泉<rt>ひらいずみ</rt></ruby>の<ruby>遺跡<rt>いせき</rt></ruby>から<ruby>出土<rt>しゅつど</rt></ruby>した<ruby>木片<rt>もくへん</rt></ruby>に<ruby>描<rt>えが</rt></ruby>かれたカエルの<ruby>落書<rt>らくが</rt></ruby>き（カエル<ruby>戯画<rt>ぎが</rt></ruby>）がモチーフで、ぽっこりしたおなかがチャームポイントです。そのカエル<ruby>戯画<rt>ぎが</rt></ruby>は<ruby>国宝<rt>こくほう</rt></ruby>の「<ruby>鳥獣人物戯画<rt>ちょうじゅうじんぶつぎが</rt></ruby>」に<ruby>似<rt>に</rt></ruby>ていて、<ruby>擬人<rt>ぎじん</rt></ruby><ruby>化<rt>か</rt></ruby>されたカエルの<ruby>絵<rt>え</rt></ruby>は<ruby>当時<rt>とうじ</rt></ruby>の<ruby>平泉<rt>ひらいずみ</rt></ruby>の<ruby>文化<rt>ぶんか</rt></ruby><ruby>環境<rt>かんきょう</rt></ruby>がとても<ruby>優<rt>すぐ</rt></ruby>れていたことを<ruby>示<rt>しめ</rt></ruby>しています。また<ruby>目<rt>め</rt></ruby>の<ruby>描<rt>か</rt></ruby>き<ruby>方<rt>かた</rt></ruby>や<ruby>腕<rt>うで</rt></ruby>の<ruby>模様<rt>もよう</rt></ruby>など<ruby>現代<rt>げんだい</rt></ruby>のマンガにも<ruby>通<rt>つう</rt></ruby>じる<ruby>表現<rt>ひょうげん</rt></ruby><ruby>方法<rt>ほうほう</rt></ruby>がとられています。",
            "origin": "つい「けろへい」と読んでしまいそうになりますが、実は読み方は「けろひら」なところがミソ。岩手県の世界遺産・平泉のＰＲキャラクターで２０１４年から活動しています。名前は平泉の「平」を表していたんですね。奥州藤原氏が政治の拠点にしていた平泉の遺跡から出土した木片に描かれたカエルの落書き（カエル戯画）がモチーフで、ぽっこりしたおなかがチャームポイントです。そのカエル戯画は国宝の「鳥獣人物戯画」に似ていて、擬人化されたカエルの絵は当時の平泉の文化環境がとても優れていたことを示しています。また目の描き方や腕の模様など現代のマンガにも通じる表現方法がとられています。"
        },
        {
            "type": "ruby",
            "ruby": "<ruby>奥州藤原氏<rt>おうしゅうふじわらし</rt></ruby>は<ruby>平安時代<rt>へいあんじだい</rt></ruby><ruby>末期<rt>まっき</rt></ruby>、<ruby>度重<rt>たびかさ</rt></ruby>なる<ruby>戦<rt>いくさ</rt></ruby>で<ruby>命<rt>いのち</rt></ruby>を<ruby>落<rt>お</rt></ruby>とした<ruby>人<rt>ひと</rt></ruby>の<ruby>霊<rt>れい</rt></ruby>を<ruby>弔<rt>とむら</rt></ruby>うために<ruby>中尊寺<rt>ちゅうそんじ</rt></ruby>を<ruby>建立<rt>こんりゅう</rt></ruby>し、<ruby>平和<rt>へいわ</rt></ruby>な<ruby>世<rt>よ</rt></ruby>の<ruby>中<rt>なか</rt></ruby>を<ruby>目指<rt>めざ</rt></ruby>しました。ケロ<ruby>平<rt>ひら</rt></ruby>は<ruby>平和<rt>へいわ</rt></ruby>を<ruby>願<rt>ねが</rt></ruby>い、<ruby>万物<rt>ばんぶつ</rt></ruby>との<ruby>共生<rt>きょうせい</rt></ruby>を<ruby>理想<rt>りそう</rt></ruby>とする<ruby>平泉<rt>ひらいずみ</rt></ruby>の<ruby>理念<rt>りねん</rt></ruby>を<ruby>現代人<rt>げんだいじん</rt></ruby>に<ruby>伝<rt>つた</rt></ruby>えるため、８００<ruby>年<rt>ねん</rt></ruby>の<ruby>時<rt>とき</rt></ruby>を<ruby>超<rt>こ</rt></ruby>え、カエル<ruby>戯画<rt>ぎが</rt></ruby>から<ruby>飛<rt>と</rt></ruby>び<ruby>出<rt>だ</rt></ruby>してきました。ぴょんぴょん<ruby>跳<rt>と</rt></ruby>び<ruby>回<rt>まわ</rt></ruby>って、<ruby>岩手<rt>いわて</rt></ruby>の<ruby>魅力<rt>みりょく</rt></ruby>を<ruby>伝<rt>つた</rt></ruby>えています。（<ruby>井上<rt>いのうえ</rt></ruby><ruby>梢<rt>こずえ</rt></ruby>）",
            "origin": "奥州藤原氏は平安時代末期、度重なる戦で命を落とした人の霊を弔うために中尊寺を建立し、平和な世の中を目指しました。ケロ平は平和を願い、万物との共生を理想とする平泉の理念を現代人に伝えるため、８００年の時を超え、カエル戯画から飛び出してきました。ぴょんぴょん跳び回って、岩手の魅力を伝えています。（井上梢）"
        },
        {
            "type": "h2",
            "ruby": "「ケロ<ruby>平<rt>ひら</rt></ruby>」データ",
            "origin": "「ケロ平」データ"
        },
        {
            "type": "ruby",
            "ruby": "●<ruby>生<rt>う</rt></ruby>まれたところ：<ruby>柳之御所<rt>やなぎのごしょ</rt></ruby><ruby>遺跡<rt>いせき</rt></ruby>から<ruby>出土<rt>しゅつど</rt></ruby>した<ruby>木片<rt>もくへん</rt></ruby>＝<ruby>写真<rt>しゃしん</rt></ruby>・<ruby>岩手県<rt>いわてけん</rt></ruby><ruby>教育委員会<rt>きょういくいいんかい</rt></ruby><ruby>提供<rt>ていきょう</rt></ruby>",
            "origin": "●生まれたところ：柳之御所遺跡から出土した木片＝写真・岩手県教育委員会提供"
        },
        {
            "type": "ruby",
            "ruby": "●<ruby>生<rt>う</rt></ruby>まれた<ruby>時期<rt>じき</rt></ruby>：<ruby>平安時代<rt>へいあんじだい</rt></ruby><ruby>後期<rt>こうき</rt></ruby>",
            "origin": "●生まれた時期：平安時代後期"
        },
        {
            "type": "ruby",
            "ruby": "●<ruby>好<rt>す</rt></ruby>きな<ruby>場所<rt>ばしょ</rt></ruby>：<ruby>毛越寺<rt>もうつうじ</rt></ruby>の<ruby>浄土<rt>じょうど</rt></ruby><ruby>庭園<rt>ていえん</rt></ruby>（<ruby>池<rt>いけ</rt></ruby>）",
            "origin": "●好きな場所：毛越寺の浄土庭園（池）"
        },
        {
            "type": "ruby",
            "ruby": "●<ruby>好物<rt>こうぶつ</rt></ruby>：どぶろく",
            "origin": "●好物：どぶろく"
        },
        {
            "type": "ruby",
            "ruby": "●<ruby>苦手<rt>にがて</rt></ruby>なこと：<ruby>争<rt>あらそ</rt></ruby>いごと",
            "origin": "●苦手なこと：争いごと"
        },
        {
            "type": "ruby",
            "ruby": "●チャームポイント：ぽっこりしたおなか",
            "origin": "●チャームポイント：ぽっこりしたおなか"
        }
    ],
    "voiceurl": "",
    "movieurl": "",
    "newimage": "https://cdn.mainichi.jp/vol1/2020/09/10/20200910kei00s00s026000p/0c6.jpg?1",
    "newsmovie": "",
    "path": "appdata/daynews/articles20200910kei00s00s002000c.json"
}