{
    "id": "articles20200905kei00s00s011000c",
    "title": "政治　大阪都構想　２度目の住民投票へ",
    "ruby": "",
    "time": "2020年9月5日",
    "imgurl": "https://cdn.mainichi.jp/vol1/2020/09/05/20200905kei00s00s023000p/0c6.jpg?1",
    "fromUrl": "https://mainichi.jp/articles/20200905/kei/00s/00s/011000c",
    "body": [
        {
            "type": "ruby",
            "ruby": "<ruby>大阪市<rt>おおさかし</rt></ruby>をなくし、<ruby>四<rt>よっ</rt></ruby>つの<ruby>特別区<rt>とくべつく</rt></ruby>に<ruby>再編<rt>さいへん</rt></ruby>する「<ruby>大阪都構想<rt>おおさかとこうそう</rt></ruby>」の<ruby>設計図<rt>せっけいず</rt></ruby>にあたる<ruby>制度<rt>せいど</rt></ruby><ruby>案<rt>あん</rt></ruby>は３<ruby>日<rt>みっか</rt></ruby>、<ruby>大阪市議会<rt>おおさかしぎかい</rt></ruby>で<ruby>認<rt>みと</rt></ruby>められました。<ruby>制度<rt>せいど</rt></ruby><ruby>案<rt>あん</rt></ruby>は<ruby>大阪府議会<rt>おおさかふぎかい</rt></ruby>でも８<ruby>月<rt>がつ</rt></ruby>２８<ruby>日<rt>にち</rt></ruby>に<ruby>認<rt>みと</rt></ruby>められています。<ruby>府<rt>ふ</rt></ruby>と<ruby>市<rt>し</rt></ruby>の<ruby>議会<rt>ぎかい</rt></ruby>でそろって<ruby>認<rt>みと</rt></ruby>められたため、<ruby>新<rt>あたら</rt></ruby>しい<ruby>仕組<rt>しく</rt></ruby>みに<ruby>移<rt>うつ</rt></ruby>るのに<ruby>賛成<rt>さんせい</rt></ruby>か<ruby>反対<rt>はんたい</rt></ruby>かを<ruby>問<rt>と</rt></ruby>う<ruby>住民投票<rt>じゅうみんとうひょう</rt></ruby>を<ruby>行<rt>おこな</rt></ruby>うことが<ruby>決<rt>き</rt></ruby>まりました。",
            "origin": "大阪市をなくし、四つの特別区に再編する「大阪都構想」の設計図にあたる制度案は３日、大阪市議会で認められました。制度案は大阪府議会でも８月２８日に認められています。府と市の議会でそろって認められたため、新しい仕組みに移るのに賛成か反対かを問う住民投票を行うことが決まりました。"
        },
        {
            "type": "ruby",
            "ruby": "<ruby>大阪都構想<rt>おおさかとこうそう</rt></ruby>をめぐっては２０１５<ruby>年<rt>ねん</rt></ruby>にも<ruby>住民投票<rt>じゅうみんとうひょう</rt></ruby>が<ruby>行<rt>おこな</rt></ruby>われ、わずかな<ruby>差<rt>さ</rt></ruby>で<ruby>反対<rt>はんたい</rt></ruby>が<ruby>賛成<rt>さんせい</rt></ruby>を<ruby>上回<rt>うわまわ</rt></ruby>りました。２<ruby>度<rt>ど</rt></ruby><ruby>目<rt>め</rt></ruby>の<ruby>今回<rt>こんかい</rt></ruby>の<ruby>日程<rt>にってい</rt></ruby>は、１０<ruby>月<rt>がつ</rt></ruby>１２<ruby>日<rt>にち</rt></ruby><ruby>告示<rt>こくじ</rt></ruby>、１１<ruby>月<rt>がつ</rt></ruby>１<ruby>日<rt>ついたち</rt></ruby><ruby>投開票<rt>とうかいひょう</rt></ruby>が<ruby>有力<rt>ゆうりょく</rt></ruby>になっています。",
            "origin": "大阪都構想をめぐっては２０１５年にも住民投票が行われ、わずかな差で反対が賛成を上回りました。２度目の今回の日程は、１０月１２日告示、１１月１日投開票が有力になっています。"
        }
    ],
    "voiceurl": "",
    "movieurl": "",
    "newimage": "https://cdn.mainichi.jp/vol1/2020/09/05/20200905kei00s00s023000p/0c6.jpg?1",
    "newsmovie": "",
    "path": "appdata/daynews/articles20200905kei00s00s011000c.json"
}