{
    "id": "articles20200917kei00s00s013000c",
    "title": "政治　新総理に菅さん　最長の安倍内閣は総辞職",
    "ruby": "",
    "time": "2020年9月17日",
    "imgurl": "https://cdn.mainichi.jp/vol1/2020/09/17/20200917kei00s00s018000p/0c6.jpg?1",
    "fromUrl": "https://mainichi.jp/articles/20200917/kei/00s/00s/013000c",
    "body": [
        {
            "type": "ruby",
            "ruby": "<ruby>臨時国会<rt>りんじこっかい</rt></ruby>が１６<ruby>日<rt>にち</rt></ruby>に<ruby>始<rt>はじ</rt></ruby>まり、<ruby>衆議院<rt>しゅうぎいん</rt></ruby>と<ruby>参議院<rt>さんぎいん</rt></ruby>で<ruby>総理大臣<rt>そうりだいじん</rt></ruby>の<ruby>指名<rt>しめい</rt></ruby><ruby>選挙<rt>せんきょ</rt></ruby>が<ruby>行<rt>おこな</rt></ruby>われ、<ruby>新<rt>あたら</rt></ruby>しい<ruby>自民党<rt>じみんとう</rt></ruby><ruby>総裁<rt>そうさい</rt></ruby>となった<ruby>菅義偉<rt>すがよしひで</rt></ruby>さん（７１）が、<ruby>第<rt>だい</rt></ruby>９９<ruby>代<rt>だい</rt></ruby>の<ruby>総理大臣<rt>そうりだいじん</rt></ruby>に<ruby>指名<rt>しめい</rt></ruby>されました。<ruby>菅<rt>すが</rt></ruby>さんは<ruby>衆議院<rt>しゅうぎいん</rt></ruby><ruby>神奈川<rt>かながわ</rt></ruby>２<ruby>区<rt>く</rt></ruby>の<ruby>選出<rt>せんしゅつ</rt></ruby>ですが、<ruby>秋田県<rt>あきたけん</rt></ruby><ruby>出身<rt>しゅっしん</rt></ruby><ruby>者<rt>しゃ</rt></ruby>で<ruby>初<rt>はじ</rt></ruby>めての<ruby>総理<rt>そうり</rt></ruby>となります。",
            "origin": "臨時国会が１６日に始まり、衆議院と参議院で総理大臣の指名選挙が行われ、新しい自民党総裁となった菅義偉さん（７１）が、第９９代の総理大臣に指名されました。菅さんは衆議院神奈川２区の選出ですが、秋田県出身者で初めての総理となります。"
        },
        {
            "type": "ruby",
            "ruby": "<ruby>菅<rt>すが</rt></ruby>さんは<ruby>直<rt>ただ</rt></ruby>ちに<ruby>新<rt>あたら</rt></ruby>しい<ruby>内閣<rt>ないかく</rt></ruby>をつくる<ruby>作業<rt>さぎょう</rt></ruby>を<ruby>始<rt>はじ</rt></ruby>め、<ruby>与党<rt>よとう</rt></ruby>の<ruby>自民党<rt>じみんとう</rt></ruby>と<ruby>公明党<rt>こうめいとう</rt></ruby>による<ruby>菅内閣<rt>すがないかく</rt></ruby>を<ruby>発足<rt>ほっそく</rt></ruby>させます。<ruby>新<rt>あたら</rt></ruby>しい<ruby>内閣<rt>ないかく</rt></ruby>をつくるにあたって、<ruby>菅<rt>すが</rt></ruby>さんは「<ruby>国民<rt>こくみん</rt></ruby>のために<ruby>働<rt>はたら</rt></ruby>く<ruby>内閣<rt>ないかく</rt></ruby>をつくる」との<ruby>考<rt>かんが</rt></ruby>えを<ruby>示<rt>しめ</rt></ruby>しました。",
            "origin": "菅さんは直ちに新しい内閣をつくる作業を始め、与党の自民党と公明党による菅内閣を発足させます。新しい内閣をつくるにあたって、菅さんは「国民のために働く内閣をつくる」との考えを示しました。"
        },
        {
            "type": "ruby",
            "ruby": "これに<ruby>先立<rt>さきだ</rt></ruby>つ１６<ruby>日<rt>にち</rt></ruby><ruby>午前<rt>ごぜん</rt></ruby>、<ruby>安倍晋三内閣<rt>あべしんぞうないかく</rt></ruby>が<ruby>総<rt>そう</rt></ruby><ruby>辞職<rt>じしょく</rt></ruby>しました。２００６～０７<ruby>年<rt>ねん</rt></ruby>の<ruby>第<rt>だい</rt></ruby>１<ruby>次<rt>じ</rt></ruby><ruby>内閣<rt>ないかく</rt></ruby>をふくむ<ruby>総理<rt>そうり</rt></ruby>の<ruby>通算<rt>つうさん</rt></ruby><ruby>在任<rt>ざいにん</rt></ruby><ruby>日数<rt>にっすう</rt></ruby>は３１８８<ruby>日<rt>にち</rt></ruby>、１２<ruby>年<rt>ねん</rt></ruby>１２<ruby>月<rt>がつ</rt></ruby>の<ruby>第<rt>だい</rt></ruby>２<ruby>次<rt>じ</rt></ruby><ruby>内閣<rt>ないかく</rt></ruby><ruby>発足<rt>ほっそく</rt></ruby>からの<ruby>連続<rt>れんぞく</rt></ruby><ruby>在任<rt>ざいにん</rt></ruby><ruby>日数<rt>にっすう</rt></ruby>は２８２２<ruby>日<rt>にち</rt></ruby>で、いずれも<ruby>歴代<rt>れきだい</rt></ruby><ruby>最長<rt>さいちょう</rt></ruby>となりました。",
            "origin": "これに先立つ１６日午前、安倍晋三内閣が総辞職しました。２００６～０７年の第１次内閣をふくむ総理の通算在任日数は３１８８日、１２年１２月の第２次内閣発足からの連続在任日数は２８２２日で、いずれも歴代最長となりました。"
        }
    ],
    "voiceurl": "",
    "movieurl": "",
    "newimage": "https://cdn.mainichi.jp/vol1/2020/09/17/20200917kei00s00s018000p/0c6.jpg?1",
    "newsmovie": "",
    "path": "appdata/daynews/articles20200917kei00s00s013000c.json"
}