{
    "id": "articles20200716kei00s00s001000c",
    "title": "宮崎市",
    "ruby": "",
    "time": "2020年7月16日",
    "imgurl": "https://cdn.mainichi.jp/vol1/2015/12/18/20151218hrc00m010001000q/9.jpg?2",
    "fromUrl": "https://mainichi.jp/articles/20200716/kei/00s/00s/001000c",
    "body": [
        {
            "type": "h2",
            "ruby": "<ruby>今回<rt>こんかい</rt></ruby>のマンホールカードはこれ！",
            "origin": "今回のマンホールカードはこれ！"
        },
        {
            "type": "ruby",
            "ruby": "<ruby>気品<rt>きひん</rt></ruby>を<ruby>感<rt>かん</rt></ruby>じるデザインですね。ハナショウブは<ruby>宮崎市<rt>みやざきし</rt></ruby>の<ruby>花<rt>はな</rt></ruby>です。アヤメ<ruby>科<rt>か</rt></ruby>の<ruby>多<rt>た</rt></ruby><ruby>年<rt>ねん</rt></ruby><ruby>草<rt>そう</rt></ruby>で５<ruby>月<rt>がつ</rt></ruby>から６<ruby>月<rt>がつ</rt></ruby>に<ruby>花<rt>はな</rt></ruby>が<ruby>咲<rt>さ</rt></ruby>きます。<ruby>新緑<rt>しんりょく</rt></ruby>を<ruby>背景<rt>はいけい</rt></ruby>に<ruby>水辺<rt>みずべ</rt></ruby>に<ruby>咲<rt>さ</rt></ruby>き<ruby>乱<rt>みだ</rt></ruby>れる<ruby>様子<rt>ようす</rt></ruby>からは<ruby>情緒<rt>じょうちょ</rt></ruby>が<ruby>漂<rt>ただよ</rt></ruby>います。カラー<ruby>版<rt>ばん</rt></ruby>のマンホール<ruby>蓋<rt>ぶた</rt></ruby>は、<ruby>縁結<rt>えんむす</rt></ruby>びで<ruby>有名<rt>ゆうめい</rt></ruby>な<ruby>青島<rt>あおしま</rt></ruby><ruby>神社<rt>じんじゃ</rt></ruby>へ<ruby>続<rt>つづ</rt></ruby>く<ruby>参道<rt>さんどう</rt></ruby>にあります。＜まとめ・<ruby>井上<rt>いのうえ</rt></ruby><ruby>梢<rt>こずえ</rt></ruby>＞",
            "origin": "気品を感じるデザインですね。ハナショウブは宮崎市の花です。アヤメ科の多年草で５月から６月に花が咲きます。新緑を背景に水辺に咲き乱れる様子からは情緒が漂います。カラー版のマンホール蓋は、縁結びで有名な青島神社へ続く参道にあります。＜まとめ・井上梢＞"
        },
        {
            "type": "ruby",
            "ruby": "カード<ruby>配布<rt>はいふ</rt></ruby><ruby>場所<rt>ばしょ</rt></ruby>：<ruby>宮崎市<rt>みやざきし</rt></ruby><ruby>上下水道<rt>じょうげすいどう</rt></ruby><ruby>局<rt>きょく</rt></ruby><ruby>写真<rt>しゃしん</rt></ruby>：<ruby>宮崎市<rt>みやざきし</rt></ruby><ruby>提供<rt>ていきょう</rt></ruby>",
            "origin": "カード配布場所：宮崎市上下水道局写真：宮崎市提供"
        },
        {
            "type": "ruby",
            "ruby": "",
            "origin": ""
        }
    ],
    "voiceurl": "",
    "movieurl": "",
    "newimage": "https://cdn.mainichi.jp/vol1/2015/12/18/20151218hrc00m010001000q/9.jpg?2",
    "newsmovie": "",
    "path": "appdata/daynews/articles20200716kei00s00s001000c.json"
}