{
    "id": "articles20200630kei00s00s011000c",
    "title": "模擬問題にチャレンジ　５級　人工知能（ＡＩ）の…",
    "ruby": "",
    "time": "2020年6月30日",
    "imgurl": "https://cdn.mainichi.jp/vol1/2015/12/18/20151218hrc00m010001000q/9.jpg?2",
    "fromUrl": "https://mainichi.jp/articles/20200630/kei/00s/00s/011000c",
    "body": [
        {
            "type": "ruby",
            "ruby": "<ruby>人工知能<rt>じんこうちのう</rt></ruby>（ＡＩ）の<ruby>弱点<rt>じゃくてん</rt></ruby>の<ruby>例<rt>れい</rt></ruby>に<ruby>当<rt>あ</rt></ruby>てはまるものを、<ruby>次<rt>つぎ</rt></ruby>から<ruby>一<rt>ひと</rt></ruby>つ<ruby>選<rt>えら</rt></ruby>びなさい。",
            "origin": "人工知能（ＡＩ）の弱点の例に当てはまるものを、次から一つ選びなさい。"
        },
        {
            "type": "ruby",
            "ruby": "（１）<ruby>細<rt>こま</rt></ruby>かい<ruby>作業<rt>さぎょう</rt></ruby>を、<ruby>正確<rt>せいかく</rt></ruby>に<ruby>何回<rt>なんかい</rt></ruby>も<ruby>繰<rt>く</rt></ruby>り<ruby>返<rt>かえ</rt></ruby>すこと。",
            "origin": "（１）細かい作業を、正確に何回も繰り返すこと。"
        },
        {
            "type": "ruby",
            "ruby": "（２）<ruby>長<rt>なが</rt></ruby>い<ruby>時間<rt>じかん</rt></ruby>、<ruby>休<rt>やす</rt></ruby>まずに<ruby>働<rt>はたら</rt></ruby>き<ruby>続<rt>つづ</rt></ruby>けること。",
            "origin": "（２）長い時間、休まずに働き続けること。"
        },
        {
            "type": "ruby",
            "ruby": "（３）<ruby>人間<rt>にんげん</rt></ruby>に<ruby>指示<rt>しじ</rt></ruby>されていないことを、<ruby>自分<rt>じぶん</rt></ruby>で<ruby>判断<rt>はんだん</rt></ruby>して<ruby>実施<rt>じっし</rt></ruby>すること。",
            "origin": "（３）人間に指示されていないことを、自分で判断して実施すること。"
        },
        {
            "type": "ruby",
            "ruby": "（４）<ruby>非常<rt>ひじょう</rt></ruby>に<ruby>複雑<rt>ふくざつ</rt></ruby>な<ruby>計算<rt>けいさん</rt></ruby>を<ruby>間違<rt>まちが</rt></ruby>えずに<ruby>素早<rt>すばや</rt></ruby>く<ruby>処理<rt>しょり</rt></ruby>すること。",
            "origin": "（４）非常に複雑な計算を間違えずに素早く処理すること。"
        },
        {
            "type": "ruby",
            "ruby": "＜ヒント＞",
            "origin": "＜ヒント＞"
        },
        {
            "type": "ruby",
            "ruby": "ＡＩは<ruby>文章<rt>ぶんしょう</rt></ruby>や<ruby>物事<rt>ものごと</rt></ruby>の<ruby>意味<rt>いみ</rt></ruby>を<ruby>理解<rt>りかい</rt></ruby>するのが<ruby>苦手<rt>にがて</rt></ruby>です。",
            "origin": "ＡＩは文章や物事の意味を理解するのが苦手です。"
        },
        {
            "type": "h2",
            "ruby": "こたえ",
            "origin": "こたえ"
        },
        {
            "type": "ruby",
            "ruby": "（３）",
            "origin": "（３）"
        },
        {
            "type": "h2",
            "ruby": "ニュース<ruby>時事能力検定試験<rt>じじのうりょくけんていしけん</rt></ruby>",
            "origin": "ニュース時事能力検定試験"
        },
        {
            "type": "ruby",
            "ruby": "●ニュース<ruby>検定<rt>けんてい</rt></ruby>を、９<ruby>月<rt>がつ</rt></ruby>６<ruby>日<rt>むいか</rt></ruby>（<ruby>日<rt>にち</rt></ruby>）に<ruby>実施<rt>じっし</rt></ruby>します。",
            "origin": "●ニュース検定を、９月６日（日）に実施します。"
        },
        {
            "type": "ruby",
            "ruby": "●５<ruby>級<rt>きゅう</rt></ruby>から２<ruby>級<rt>きゅう</rt></ruby>まで、<ruby>自分<rt>じぶん</rt></ruby>の<ruby>力<rt>ちから</rt></ruby>に<ruby>合<rt>あ</rt></ruby>わせてチャレンジできます（１<ruby>級<rt>きゅう</rt></ruby>は<ruby>実施<rt>じっし</rt></ruby>しません）。",
            "origin": "●５級から２級まで、自分の力に合わせてチャレンジできます（１級は実施しません）。"
        },
        {
            "type": "ruby",
            "ruby": "●<ruby>詳<rt>くわ</rt></ruby>しくはニュース<ruby>検定<rt>けんてい</rt></ruby><ruby>公式<rt>こうしき</rt></ruby>サイトをご<ruby>覧<rt>らん</rt></ruby>ください。<ruby>右<rt>みぎ</rt></ruby>のＱＲコードまたは<ruby>下<rt>した</rt></ruby>のＵＲＬよりアクセスできます。",
            "origin": "●詳しくはニュース検定公式サイトをご覧ください。右のＱＲコードまたは下のＵＲＬよりアクセスできます。"
        },
        {
            "type": "ruby",
            "ruby": "<ruby>問<rt>と</rt></ruby>い<ruby>合<rt>あ</rt></ruby>わせは０３・５２０９・０５５３（<ruby>平日<rt>へいじつ</rt></ruby>１０～１７<ruby>時<rt>じ</rt></ruby>）",
            "origin": "問い合わせは０３・５２０９・０５５３（平日１０～１７時）"
        },
        {
            "type": "ruby",
            "ruby": "ｈｔｔｐｓ：／／ｗｗｗ．ｎｅｗｓｋｅｎｔｅｉ．ｊｐ／",
            "origin": "ｈｔｔｐｓ：／／ｗｗｗ．ｎｅｗｓｋｅｎｔｅｉ．ｊｐ／"
        }
    ],
    "voiceurl": "",
    "movieurl": "",
    "newimage": "https://cdn.mainichi.jp/vol1/2015/12/18/20151218hrc00m010001000q/9.jpg?2",
    "newsmovie": "",
    "path": "appdata/daynews/articles20200630kei00s00s011000c.json"
}