{
    "id": "articles20201114kei00s00s010000c",
    "title": "プレイステーション",
    "ruby": "",
    "time": "2020年11月14日",
    "imgurl": "https://cdn.mainichi.jp/vol1/2015/12/18/20151218hrc00m010001000q/9.jpg?2",
    "fromUrl": "https://mainichi.jp/articles/20201114/kei/00s/00s/010000c",
    "body": [
        {
            "type": "ruby",
            "ruby": "ソニーが<ruby>販売<rt>はんばい</rt></ruby>する<ruby>家庭<rt>かてい</rt></ruby><ruby>用<rt>よう</rt></ruby>の<ruby>据<rt>す</rt></ruby>え<ruby>置<rt>お</rt></ruby>き<ruby>型<rt>がた</rt></ruby>ゲーム<ruby>機<rt>き</rt></ruby>です。<ruby>仕事<rt>しごと</rt></ruby>で<ruby>使<rt>つか</rt></ruby>うコンピューターを「ワークステーション」と<ruby>呼<rt>よ</rt></ruby>ぶのに<ruby>対<rt>たい</rt></ruby>し、<ruby>遊<rt>あそ</rt></ruby>び（プレー）で<ruby>使<rt>つか</rt></ruby>うという<ruby>意味<rt>いみ</rt></ruby>で<ruby>名付<rt>なづ</rt></ruby>けられました。<ruby>初代<rt>しょだい</rt></ruby>は１９９４<ruby>年<rt>ねん</rt></ruby>１２<ruby>月<rt>がつ</rt></ruby>に<ruby>発売<rt>はつばい</rt></ruby>されました。",
            "origin": "ソニーが販売する家庭用の据え置き型ゲーム機です。仕事で使うコンピューターを「ワークステーション」と呼ぶのに対し、遊び（プレー）で使うという意味で名付けられました。初代は１９９４年１２月に発売されました。"
        }
    ],
    "voiceurl": "",
    "movieurl": "",
    "newimage": "https://cdn.mainichi.jp/vol1/2015/12/18/20151218hrc00m010001000q/9.jpg?2",
    "newsmovie": "",
    "path": "appdata/daynews/articles20201114kei00s00s010000c.json"
}