{
    "id": "articles20201028kei00s00s013000c",
    "title": "作家３人、小学生に読んでほしいお薦めの本は？（その１）",
    "ruby": "",
    "time": "2020年10月28日",
    "imgurl": "https://cdn.mainichi.jp/vol1/2020/10/28/20201028kei00s00s020000p/0c6.jpg?1",
    "fromUrl": "https://mainichi.jp/articles/20201028/kei/00s/00s/013000c",
    "body": [
        {
            "type": "ruby",
            "ruby": "<ruby>秋<rt>あき</rt></ruby>は<ruby>古<rt>ふる</rt></ruby>くから、<ruby>読書<rt>どくしょ</rt></ruby>に<ruby>合<rt>あ</rt></ruby>った<ruby>季節<rt>きせつ</rt></ruby>といわれます。そこで<ruby>毎小<rt>まいしょう</rt></ruby>では「<ruby>読書<rt>どくしょ</rt></ruby>の<ruby>秋<rt>あき</rt></ruby>」にちなみ、３<ruby>人<rt>にん</rt></ruby>の<ruby>作家<rt>さっか</rt></ruby>にお<ruby>薦<rt>すす</rt></ruby>めの３<ruby>冊<rt>さつ</rt></ruby>を<ruby>選<rt>えら</rt></ruby>んでもらいました。<ruby>新型<rt>しんがた</rt></ruby>コロナウイルスの<ruby>影響<rt>えいきょう</rt></ruby>で、<ruby>家<rt>いえ</rt></ruby>ですごす<ruby>時間<rt>じかん</rt></ruby>が<ruby>増<rt>ふ</rt></ruby>えた<ruby>今<rt>いま</rt></ruby>、<ruby>読書<rt>どくしょ</rt></ruby>を<ruby>通<rt>とお</rt></ruby>して<ruby>未知<rt>みち</rt></ruby>の<ruby>世界<rt>せかい</rt></ruby>にふれてみませんか。【<ruby>長岡<rt>ながおか</rt></ruby><ruby>平助<rt>へいすけ</rt></ruby>】",
            "origin": "秋は古くから、読書に合った季節といわれます。そこで毎小では「読書の秋」にちなみ、３人の作家にお薦めの３冊を選んでもらいました。新型コロナウイルスの影響で、家ですごす時間が増えた今、読書を通して未知の世界にふれてみませんか。【長岡平助】"
        },
        {
            "type": "h2",
            "ruby": "<ruby>書<rt>か</rt></ruby>き<ruby>手<rt>て</rt></ruby>が<ruby>伝<rt>つた</rt></ruby>える<ruby>思<rt>おも</rt></ruby>い",
            "origin": "書き手が伝える思い"
        },
        {
            "type": "ruby",
            "ruby": "みなさんはふだん、どんな<ruby>本<rt>ほん</rt></ruby>を<ruby>読<rt>よ</rt></ruby>みますか？",
            "origin": "みなさんはふだん、どんな本を読みますか？"
        },
        {
            "type": "ruby",
            "ruby": "<ruby>小説<rt>しょうせつ</rt></ruby>？<ruby>図鑑<rt>ずかん</rt></ruby>？<ruby>絵本<rt>えほん</rt></ruby>？",
            "origin": "小説？図鑑？絵本？"
        },
        {
            "type": "ruby",
            "ruby": "それともマンガ？",
            "origin": "それともマンガ？"
        },
        {
            "type": "ruby",
            "ruby": "<ruby>今回<rt>こんかい</rt></ruby>、お<ruby>薦<rt>すす</rt></ruby>めの<ruby>本<rt>ほん</rt></ruby>を<ruby>選<rt>えら</rt></ruby>んでくれたのは、<ruby>物語<rt>ものがたり</rt></ruby>の<ruby>書<rt>か</rt></ruby>き<ruby>手<rt>て</rt></ruby>として<ruby>高<rt>たか</rt></ruby>い<ruby>評価<rt>ひょうか</rt></ruby>を<ruby>受<rt>う</rt></ruby>ける３<ruby>人<rt>にん</rt></ruby>の<ruby>作家<rt>さっか</rt></ruby>です。",
            "origin": "今回、お薦めの本を選んでくれたのは、物語の書き手として高い評価を受ける３人の作家です。"
        },
        {
            "type": "ruby",
            "ruby": "<ruby>阿部智里<rt>あべちさと</rt></ruby>さんは１９９１<ruby>年<rt>ねん</rt></ruby><ruby>生<rt>う</rt></ruby>まれ。２０１２<ruby>年<rt>ねん</rt></ruby>、<ruby>人間<rt>にんげん</rt></ruby>に<ruby>変身<rt>へんしん</rt></ruby>できる<ruby>三本<rt>さんぼん</rt></ruby><ruby>足<rt>あし</rt></ruby>の<ruby>伝説<rt>でんせつ</rt></ruby>の<ruby>烏<rt>からす</rt></ruby>「<ruby>八咫烏<rt>やたがらす</rt></ruby>」たちの<ruby>活躍<rt>かつやく</rt></ruby>を<ruby>描<rt>えが</rt></ruby>いたファンタジー<ruby>小説<rt>しょうせつ</rt></ruby>「<ruby>烏<rt>からす</rt></ruby>に<ruby>単<rt>ひとえ</rt></ruby>は<ruby>似合<rt>にあ</rt></ruby>わない」（<ruby>文芸春秋<rt>ぶんげいしゅんじゅう</rt></ruby>）で、<ruby>松本清張賞<rt>まつもとせいちょうしょう</rt></ruby>を<ruby>受賞<rt>じゅしょう</rt></ruby>しました。この<ruby>時<rt>とき</rt></ruby>、<ruby>阿部<rt>あべ</rt></ruby>さんは<ruby>大学<rt>だいがく</rt></ruby><ruby>在学中<rt>ざいがくちゅう</rt></ruby>で、２０<ruby>歳<rt>さい</rt></ruby>。<ruby>史上<rt>しじょう</rt></ruby><ruby>最<rt>さい</rt></ruby><ruby>年<rt>ねん</rt></ruby><ruby>少<rt>しょう</rt></ruby>でした。「<ruby>八咫烏<rt>やたがらす</rt></ruby>」シリーズは、これまでに１５０<ruby>万<rt>まん</rt></ruby><ruby>部<rt>ぶ</rt></ruby>を<ruby>超<rt>こ</rt></ruby>え、シリーズの<ruby>最新作<rt>さいしんさく</rt></ruby>「<ruby>楽園<rt>らくえん</rt></ruby>の<ruby>烏<rt>からす</rt></ruby>」が９<ruby>月<rt>がつ</rt></ruby>に<ruby>発売<rt>はつばい</rt></ruby>されました。",
            "origin": "阿部智里さんは１９９１年生まれ。２０１２年、人間に変身できる三本足の伝説の烏「八咫烏」たちの活躍を描いたファンタジー小説「烏に単は似合わない」（文芸春秋）で、松本清張賞を受賞しました。この時、阿部さんは大学在学中で、２０歳。史上最年少でした。「八咫烏」シリーズは、これまでに１５０万部を超え、シリーズの最新作「楽園の烏」が９月に発売されました。"
        },
        {
            "type": "ruby",
            "ruby": "<ruby>辻村深月<rt>つじむらみづき</rt></ruby>さんは１９８０<ruby>年<rt>ねん</rt></ruby><ruby>生<rt>う</rt></ruby>まれ。<ruby>毎小<rt>まいしょう</rt></ruby>で<ruby>毎月<rt>まいつき</rt></ruby><ruby>第<rt>だい</rt></ruby>１<ruby>日曜日<rt>にちようび</rt></ruby>（<ruby>一部地域<rt>いちぶちいき</rt></ruby>は<ruby>翌日<rt>よくじつ</rt></ruby>）に「『あなたの<ruby>言葉<rt>ことば</rt></ruby>』を」を<ruby>連載<rt>れんさい</rt></ruby><ruby>中<rt>ちゅう</rt></ruby>です。<ruby>辻村<rt>つじむら</rt></ruby>さんは２００４<ruby>年<rt>ねん</rt></ruby>「<ruby>冷<rt>つめ</rt></ruby>たい<ruby>校舎<rt>こうしゃ</rt></ruby>の<ruby>時<rt>とき</rt></ruby>は<ruby>止<rt>と</rt></ruby>まる」（<ruby>講談社<rt>こうだんしゃ</rt></ruby>）でメフィスト<ruby>賞<rt>しょう</rt></ruby>を<ruby>受賞<rt>じゅしょう</rt></ruby>しデビュー。１２<ruby>年<rt>ねん</rt></ruby>に「<ruby>鍵<rt>かぎ</rt></ruby>のない<ruby>夢<rt>ゆめ</rt></ruby>を<ruby>見<rt>み</rt></ruby>る」（<ruby>文芸春秋<rt>ぶんげいしゅんじゅう</rt></ruby>）で<ruby>直木賞<rt>なおきしょう</rt></ruby>を<ruby>受賞<rt>じゅしょう</rt></ruby>。１８<ruby>年<rt>ねん</rt></ruby>、<ruby>学校<rt>がっこう</rt></ruby>で<ruby>居場所<rt>いばしょ</rt></ruby>をなくした<ruby>中学生<rt>ちゅうがくせい</rt></ruby>たちを<ruby>描<rt>えが</rt></ruby>いた「かがみの<ruby>孤城<rt>こじょう</rt></ruby>」（ポプラ<ruby>社<rt>しゃ</rt></ruby>）で<ruby>本屋大賞<rt>ほんやたいしょう</rt></ruby>を<ruby>受賞<rt>じゅしょう</rt></ruby>しました。",
            "origin": "辻村深月さんは１９８０年生まれ。毎小で毎月第１日曜日（一部地域は翌日）に「『あなたの言葉』を」を連載中です。辻村さんは２００４年「冷たい校舎の時は止まる」（講談社）でメフィスト賞を受賞しデビュー。１２年に「鍵のない夢を見る」（文芸春秋）で直木賞を受賞。１８年、学校で居場所をなくした中学生たちを描いた「かがみの孤城」（ポプラ社）で本屋大賞を受賞しました。"
        },
        {
            "type": "ruby",
            "ruby": "<ruby>早見和真<rt>はやみかずまさ</rt></ruby>さんは１９７７<ruby>年<rt>ねん</rt></ruby><ruby>生<rt>う</rt></ruby>まれ。２００８<ruby>年<rt>ねん</rt></ruby>、<ruby>野球<rt>やきゅう</rt></ruby><ruby>強豪<rt>きょうごう</rt></ruby><ruby>校<rt>こう</rt></ruby>の<ruby>補欠<rt>ほけつ</rt></ruby>の<ruby>姿<rt>すがた</rt></ruby>を<ruby>生<rt>い</rt></ruby>き<ruby>生<rt>い</rt></ruby>きと<ruby>描<rt>えが</rt></ruby>いた「ひゃくはち」（<ruby>集英社<rt>しゅうえいしゃ</rt></ruby>）でデビュー。１５<ruby>年<rt>ねん</rt></ruby>に「イノセント・デイズ」（<ruby>新潮社<rt>しんちょうしゃ</rt></ruby>）で<ruby>日本推理作家協会賞<rt>にほんすいりさっかきょうかいしょう</rt></ruby>に<ruby>輝<rt>かがや</rt></ruby>き、<ruby>今年<rt>ことし</rt></ruby>「ザ・ロイヤルファミリー」（<ruby>新潮社<rt>しんちょうしゃ</rt></ruby>）で<ruby>山本周五郎賞<rt>やまもとしゅうごろうしょう</rt></ruby>を<ruby>受賞<rt>じゅしょう</rt></ruby>。<ruby>野球<rt>やきゅう</rt></ruby>の<ruby>強豪<rt>きょうごう</rt></ruby>として<ruby>知<rt>し</rt></ruby>られる<ruby>神奈川県<rt>かながわけん</rt></ruby>の<ruby>桐蔭学園<rt>とういんがくえん</rt></ruby>で、<ruby>甲子園<rt>こうしえん</rt></ruby>を<ruby>目指<rt>めざ</rt></ruby>していたことでも<ruby>知<rt>し</rt></ruby>られます。",
            "origin": "早見和真さんは１９７７年生まれ。２００８年、野球強豪校の補欠の姿を生き生きと描いた「ひゃくはち」（集英社）でデビュー。１５年に「イノセント・デイズ」（新潮社）で日本推理作家協会賞に輝き、今年「ザ・ロイヤルファミリー」（新潮社）で山本周五郎賞を受賞。野球の強豪として知られる神奈川県の桐蔭学園で、甲子園を目指していたことでも知られます。"
        },
        {
            "type": "ruby",
            "ruby": "<ruby>本<rt>ほん</rt></ruby>の<ruby>世界<rt>せかい</rt></ruby>で<ruby>活躍<rt>かつやく</rt></ruby>する３<ruby>人<rt>にん</rt></ruby>が、<ruby>本<rt>ほん</rt></ruby>を<ruby>通<rt>とお</rt></ruby>して<ruby>小学生<rt>しょうがくせい</rt></ruby>のみなさんに<ruby>伝<rt>つた</rt></ruby>えたかった<ruby>思<rt>おも</rt></ruby>いとは――。＝２<ruby>面<rt>めん</rt></ruby>につづく",
            "origin": "本の世界で活躍する３人が、本を通して小学生のみなさんに伝えたかった思いとは――。＝２面につづく"
        },
        {
            "type": "h2",
            "ruby": "<ruby>阿部智里<rt>あべちさと</rt></ruby>さん",
            "origin": "阿部智里さん"
        },
        {
            "type": "ruby",
            "ruby": "とりかえばや<ruby>物語<rt>ものがたり</rt></ruby><ruby>田辺聖子<rt>たなべせいこ</rt></ruby><ruby>著<rt>ちょ</rt></ruby>（<ruby>文春文庫<rt>ぶんしゅんぶんこ</rt></ruby>）",
            "origin": "とりかえばや物語田辺聖子著（文春文庫）"
        },
        {
            "type": "ruby",
            "ruby": "<ruby>白狐魔記<rt>しらこまき</rt></ruby><ruby>源平<rt>げんぺい</rt></ruby>の<ruby>風<rt>かぜ</rt></ruby><ruby>斉藤洋<rt>さいとうひろし</rt></ruby><ruby>著<rt>ちょ</rt></ruby>（<ruby>偕成社<rt>かいせいしゃ</rt></ruby>）",
            "origin": "白狐魔記源平の風斉藤洋著（偕成社）"
        },
        {
            "type": "ruby",
            "ruby": "<ruby>南総里見八犬伝<rt>なんそうさとみはっけんでん</rt></ruby>〈１〉<ruby>妖刀<rt>ようとう</rt></ruby><ruby>村雨丸<rt>むらさめまる</rt></ruby><ruby>滝沢馬琴<rt>たきざわばきん</rt></ruby>・<ruby>浜<rt>はま</rt></ruby>たかや<ruby>著<rt>ちょ</rt></ruby>（<ruby>偕成社<rt>かいせいしゃ</rt></ruby>）",
            "origin": "南総里見八犬伝〈１〉妖刀村雨丸滝沢馬琴・浜たかや著（偕成社）"
        },
        {
            "type": "h2",
            "ruby": "<ruby>辻村<rt>つじむら</rt></ruby><ruby>深月<rt>みづき</rt></ruby>さん",
            "origin": "辻村深月さん"
        },
        {
            "type": "ruby",
            "ruby": "くまの<ruby>子<rt>こ</rt></ruby>ウーフ<ruby>神沢利子<rt>かんざわとしこ</rt></ruby><ruby>著<rt>ちょ</rt></ruby>（ポプラ<ruby>社<rt>しゃ</rt></ruby>）",
            "origin": "くまの子ウーフ神沢利子著（ポプラ社）"
        },
        {
            "type": "ruby",
            "ruby": "うわさのズッコケ<ruby>株式会社<rt>かぶしきがいしゃ</rt></ruby><ruby>那須正幹<rt>なすまさもと</rt></ruby><ruby>著<rt>ちょ</rt></ruby>（ポプラ<ruby>社<rt>しゃ</rt></ruby>）",
            "origin": "うわさのズッコケ株式会社那須正幹著（ポプラ社）"
        },
        {
            "type": "ruby",
            "ruby": "まっくろいたちのレストラン<ruby>島本理生<rt>しまもとりお</rt></ruby><ruby>著<rt>ちょ</rt></ruby>（<ruby>岩崎書店<rt>いわさきしょてん</rt></ruby>）",
            "origin": "まっくろいたちのレストラン島本理生著（岩崎書店）"
        },
        {
            "type": "h2",
            "ruby": "<ruby>早見和真<rt>はやみかずまさ</rt></ruby>さん",
            "origin": "早見和真さん"
        },
        {
            "type": "ruby",
            "ruby": "クラスメイツ（<ruby>前期<rt>ぜんき</rt></ruby>・<ruby>後期<rt>こうき</rt></ruby>）<ruby>森<rt>もり</rt></ruby><ruby>絵都<rt>えと</rt></ruby><ruby>著<rt>ちょ</rt></ruby>（<ruby>偕成社<rt>かいせいしゃ</rt></ruby>）",
            "origin": "クラスメイツ（前期・後期）森絵都著（偕成社）"
        },
        {
            "type": "ruby",
            "ruby": "<ruby>小説<rt>しょうせつ</rt></ruby>「<ruby>映画<rt>えいが</rt></ruby>ドラえもんのび<ruby>太<rt>た</rt></ruby>の<ruby>月面<rt>げつめん</rt></ruby><ruby>探査<rt>たんさ</rt></ruby><ruby>記<rt>き</rt></ruby>」<ruby>辻村深月<rt>つじむらみづき</rt></ruby><ruby>著<rt>ちょ</rt></ruby>（<ruby>小学館<rt>しょうがくかん</rt></ruby>）",
            "origin": "小説「映画ドラえもんのび太の月面探査記」辻村深月著（小学館）"
        },
        {
            "type": "ruby",
            "ruby": "かなしきデブ<ruby>猫<rt>ねこ</rt></ruby>ちゃん<ruby>早見和真<rt>はやみかずまさ</rt></ruby>・かのうかりん<ruby>著<rt>ちょ</rt></ruby>（<ruby>愛媛新聞社<rt>えひめしんぶんしゃ</rt></ruby>）",
            "origin": "かなしきデブ猫ちゃん早見和真・かのうかりん著（愛媛新聞社）"
        }
    ],
    "voiceurl": "",
    "movieurl": "",
    "newimage": "https://cdn.mainichi.jp/vol1/2020/10/28/20201028kei00s00s020000p/0c6.jpg?1",
    "newsmovie": "",
    "path": "appdata/daynews/articles20201028kei00s00s013000c.json"
}