{
    "id": "articles20200704kei00s00s016000c",
    "title": "ここに注目！／２９７　アメリカ　社会を映す「壁」",
    "ruby": "",
    "time": "2020年7月4日",
    "imgurl": "https://cdn.mainichi.jp/vol1/2020/07/04/20200704kei00s00s020000p/0c6.jpg?1",
    "fromUrl": "https://mainichi.jp/articles/20200704/kei/00s/00s/016000c",
    "body": [
        {
            "type": "ruby",
            "ruby": "「<ruby>子<rt>こ</rt></ruby>どもは<ruby>社会<rt>しゃかい</rt></ruby>を<ruby>映<rt>うつ</rt></ruby>す<ruby>鏡<rt>かがみ</rt></ruby>」とよく<ruby>言<rt>い</rt></ruby>われますが、アメリカでは「<ruby>壁<rt>かべ</rt></ruby>」に<ruby>社会<rt>しゃかい</rt></ruby>の<ruby>状況<rt>じょうきょう</rt></ruby>が<ruby>表<rt>あらわ</rt></ruby>れます。アーティストらが<ruby>人々<rt>ひとびと</rt></ruby>に<ruby>伝<rt>つた</rt></ruby>えたいメッセージを<ruby>街中<rt>まちなか</rt></ruby>の<ruby>壁<rt>かべ</rt></ruby>などに<ruby>絵<rt>え</rt></ruby>や<ruby>文字<rt>もじ</rt></ruby>で<ruby>描<rt>えが</rt></ruby>くからです。<ruby>大<rt>おお</rt></ruby>きな<ruby>出来事<rt>できごと</rt></ruby>があった<ruby>時<rt>とき</rt></ruby>や、<ruby>社会<rt>しゃかい</rt></ruby>に<ruby>不安<rt>ふあん</rt></ruby>が<ruby>広<rt>ひろ</rt></ruby>がった<ruby>場合<rt>ばあい</rt></ruby>は、そうした「<ruby>作品<rt>さくひん</rt></ruby>」が<ruby>特<rt>とく</rt></ruby>に<ruby>増<rt>ふ</rt></ruby>えます。",
            "origin": "「子どもは社会を映す鏡」とよく言われますが、アメリカでは「壁」に社会の状況が表れます。アーティストらが人々に伝えたいメッセージを街中の壁などに絵や文字で描くからです。大きな出来事があった時や、社会に不安が広がった場合は、そうした「作品」が特に増えます。"
        },
        {
            "type": "ruby",
            "ruby": "<ruby>最近<rt>さいきん</rt></ruby>では、<ruby>新型<rt>しんがた</rt></ruby>コロナウイルスの<ruby>感染<rt>かんせん</rt></ruby><ruby>防止<rt>ぼうし</rt></ruby>のために「<ruby>家<rt>いえ</rt></ruby>にいよう」と<ruby>呼<rt>よ</rt></ruby>びかけたり＝<ruby>写真<rt>しゃしん</rt></ruby>＜上＞（うえ）、<ruby>白人<rt>はくじん</rt></ruby><ruby>警官<rt>けいかん</rt></ruby>による<ruby>暴力<rt>ぼうりょく</rt></ruby>で、<ruby>黒人<rt>こくじん</rt></ruby><ruby>男性<rt>だんせい</rt></ruby>が<ruby>死亡<rt>しぼう</rt></ruby>した<ruby>事件<rt>じけん</rt></ruby>を<ruby>受<rt>う</rt></ruby>け、「ブラック・ライブズ・マター（<ruby>黒人<rt>こくじん</rt></ruby>の<ruby>命<rt>いのち</rt></ruby>は<ruby>大切<rt>たいせつ</rt></ruby>だ）」と<ruby>人種差別<rt>じんしゅさべつ</rt></ruby>に<ruby>抗議<rt>こうぎ</rt></ruby>したりする<ruby>壁画<rt>へきが</rt></ruby>＝<ruby>写真<rt>しゃしん</rt></ruby>＜下＞（した）＝が<ruby>多<rt>おお</rt></ruby>く<ruby>見<rt>み</rt></ruby>られます。",
            "origin": "最近では、新型コロナウイルスの感染防止のために「家にいよう」と呼びかけたり＝写真＜上＞（うえ）、白人警官による暴力で、黒人男性が死亡した事件を受け、「ブラック・ライブズ・マター（黒人の命は大切だ）」と人種差別に抗議したりする壁画＝写真＜下＞（した）＝が多く見られます。"
        },
        {
            "type": "ruby",
            "ruby": "こうした<ruby>手描<rt>てが</rt></ruby>きの<ruby>壁画<rt>へきが</rt></ruby>は、<ruby>街<rt>まち</rt></ruby>の<ruby>景色<rt>けしき</rt></ruby>に<ruby>彩<rt>いろど</rt></ruby>りや<ruby>温<rt>あたた</rt></ruby>かみを<ruby>与<rt>あた</rt></ruby>えています。<ruby>日本<rt>にっぽん</rt></ruby>では「<ruby>落書<rt>らくが</rt></ruby>き」というイメージが<ruby>強<rt>つよ</rt></ruby>く、<ruby>厳<rt>きび</rt></ruby>しく<ruby>規制<rt>きせい</rt></ruby>されていますね。<ruby>許可<rt>きょか</rt></ruby>を<ruby>取<rt>と</rt></ruby>らずに<ruby>乱暴<rt>らんぼう</rt></ruby>な<ruby>文字<rt>もじ</rt></ruby>などを<ruby>描<rt>えが</rt></ruby>くのは<ruby>良<rt>よ</rt></ruby>くありませんが、みなさんは<ruby>壁画<rt>へきが</rt></ruby>についてどう<ruby>思<rt>おも</rt></ruby>いますか。【ロサンゼルス・<ruby>福永<rt>ふくなが</rt></ruby><ruby>方人<rt>ほうじん</rt></ruby>、<ruby>写真<rt>しゃしん</rt></ruby>も】",
            "origin": "こうした手描きの壁画は、街の景色に彩りや温かみを与えています。日本では「落書き」というイメージが強く、厳しく規制されていますね。許可を取らずに乱暴な文字などを描くのは良くありませんが、みなさんは壁画についてどう思いますか。【ロサンゼルス・福永方人、写真も】"
        },
        {
            "type": "ruby",
            "ruby": "<ruby>国名<rt>こくめい</rt></ruby>アメリカ<ruby>合衆国<rt>がっしゅうこく</rt></ruby>",
            "origin": "国名アメリカ合衆国"
        },
        {
            "type": "ruby",
            "ruby": "<ruby>首都<rt>しゅと</rt></ruby>ワシントンＤ．Ｃ．",
            "origin": "首都ワシントンＤ．Ｃ．"
        },
        {
            "type": "ruby",
            "ruby": "<ruby>面積<rt>めんせき</rt></ruby>９８３<ruby>万<rt>まん</rt></ruby>３５１７<ruby>平方<rt>へいほう</rt></ruby>キロメートル",
            "origin": "面積９８３万３５１７平方キロメートル"
        },
        {
            "type": "ruby",
            "ruby": "<ruby>人口<rt>じんこう</rt></ruby>３<ruby>億<rt>おく</rt></ruby>６６６０<ruby>万<rt>まん</rt></ruby><ruby>人<rt>にん</rt></ruby>（２０１９<ruby>年<rt>ねん</rt></ruby><ruby>推定<rt>すいてい</rt></ruby>）",
            "origin": "人口３億６６６０万人（２０１９年推定）"
        }
    ],
    "voiceurl": "",
    "movieurl": "",
    "newimage": "https://cdn.mainichi.jp/vol1/2020/07/04/20200704kei00s00s020000p/0c6.jpg?1",
    "newsmovie": "",
    "path": "appdata/daynews/articles20200704kei00s00s016000c.json"
}