{
    "id": "articles20201030kei00s00s003000c",
    "title": "編集部から　七五三どうしてる？",
    "ruby": "",
    "time": "2020年10月30日",
    "imgurl": "https://cdn.mainichi.jp/vol1/2015/12/18/20151218hrc00m010001000q/9.jpg?2",
    "fromUrl": "https://mainichi.jp/articles/20201030/kei/00s/00s/003000c",
    "body": [
        {
            "type": "ruby",
            "ruby": "<ruby>子<rt>こ</rt></ruby>どもたちの<ruby>健<rt>すこ</rt></ruby>やかな<ruby>成長<rt>せいちょう</rt></ruby>をお<ruby>祝<rt>いわ</rt></ruby>いする<ruby>日本<rt>にっぽん</rt></ruby>の<ruby>伝統<rt>でんとう</rt></ruby><ruby>行事<rt>ぎょうじ</rt></ruby>、<ruby>七五三<rt>しちごさん</rt></ruby>。<ruby>今年<rt>ことし</rt></ruby>は<ruby>新型<rt>しんがた</rt></ruby>コロナウイルスが<ruby>広<rt>ひろ</rt></ruby>がっていますが、<ruby>思<rt>おも</rt></ruby>い<ruby>通<rt>どお</rt></ruby>りのお<ruby>祝<rt>いわ</rt></ruby>いはできますか。<ruby>何<rt>なに</rt></ruby>か<ruby>工夫<rt>くふう</rt></ruby>をしていますか。<ruby>七五三<rt>しちごさん</rt></ruby>の<ruby>様子<rt>ようす</rt></ruby>を<ruby>教<rt>おし</rt></ruby>えてください。<ruby>名前<rt>なまえ</rt></ruby>（ふりがなも）▽<ruby>学<rt>がく</rt></ruby><ruby>年<rt>ねん</rt></ruby>▽<ruby>連絡先<rt>れんらくさき</rt></ruby>（<ruby>電話番号<rt>でんわばんごう</rt></ruby>かメールアドレス）▽<ruby>住所<rt>じゅうしょ</rt></ruby>▽<ruby>七五三<rt>しちごさん</rt></ruby>の<ruby>様子<rt>ようす</rt></ruby>や<ruby>工夫<rt>くふう</rt></ruby>――を<ruby>書<rt>か</rt></ruby>いて（<ruby>写真<rt>しゃしん</rt></ruby>があれば<ruby>添付<rt>てんぷ</rt></ruby>）、メールの<ruby>件名<rt>けんめい</rt></ruby>を「<ruby>七五三<rt>しちごさん</rt></ruby>」にしてｍａｉｓｈｏｕ＠ｍａｉｎｉｃｈｉ．ｃｏ．ｊｐへ。<ruby>締<rt>し</rt></ruby>め<ruby>切<rt>き</rt></ruby>りは１１<ruby>月<rt>がつ</rt></ruby>４（よっ）<ruby>日<rt>か</rt></ruby>。",
            "origin": "子どもたちの健やかな成長をお祝いする日本の伝統行事、七五三。今年は新型コロナウイルスが広がっていますが、思い通りのお祝いはできますか。何か工夫をしていますか。七五三の様子を教えてください。名前（ふりがなも）▽学年▽連絡先（電話番号かメールアドレス）▽住所▽七五三の様子や工夫――を書いて（写真があれば添付）、メールの件名を「七五三」にしてｍａｉｓｈｏｕ＠ｍａｉｎｉｃｈｉ．ｃｏ．ｊｐへ。締め切りは１１月４（よっ）日。"
        },
        {
            "type": "ruby",
            "ruby": "",
            "origin": ""
        }
    ],
    "voiceurl": "",
    "movieurl": "",
    "newimage": "https://cdn.mainichi.jp/vol1/2015/12/18/20151218hrc00m010001000q/9.jpg?2",
    "newsmovie": "",
    "path": "appdata/daynews/articles20201030kei00s00s003000c.json"
}